bin/__init__.py
bin/acc2gtdb_tax.py
bin/gtdb_to_diamond.py
bin/gtdb_to_taxdump.py
bin/lineage2taxid.py
bin/ncbi-gtdb_map.py
gtdb2td/Dmp.py
gtdb2td/Graph.py
gtdb2td/IO.py
gtdb2td/Utils.py
gtdb2td/__init__.py
gtdb_to_taxdump-0.1.9.data/scripts/acc2gtdb_tax.py
gtdb_to_taxdump-0.1.9.data/scripts/gtdb_to_diamond.py
gtdb_to_taxdump-0.1.9.data/scripts/gtdb_to_taxdump.py
gtdb_to_taxdump-0.1.9.data/scripts/lineage2taxid.py
gtdb_to_taxdump-0.1.9.data/scripts/ncbi-gtdb_map.py
gtdb_to_taxdump-0.1.9.dist-info/LICENSE
gtdb_to_taxdump-0.1.9.dist-info/METADATA
gtdb_to_taxdump-0.1.9.dist-info/WHEEL
gtdb_to_taxdump-0.1.9.dist-info/top_level.txt
gtdb_to_taxdump-0.1.9.dist-info/RECORD
